blox/__init__.py
blox/blocks.py
blox/interfaces.py
blox/visualize.py
jax_blox-0.1.5.dist-info/METADATA
jax_blox-0.1.5.dist-info/WHEEL
jax_blox-0.1.5.dist-info/licenses/LICENSE
jax_blox-0.1.5.dist-info/RECORD
