Metadata-Version: 2.4
Name: jax-blox
Version: 0.1.5
Summary: A functional and lightweight neural network library for JAX.
Project-URL: Repository, https://github.com/hamzamerzic/blox
Author-email: Hamza Merzić <hamzamerzic@gmail.com>
License: MIT License
License-File: LICENSE
Classifier: Development Status :: 3 - Alpha
Classifier: Intended Audience :: Education
Classifier: Intended Audience :: Science/Research
Classifier: License :: OSI Approved :: MIT License
Classifier: Programming Language :: Python :: 3
Classifier: Programming Language :: Python :: 3.11
Classifier: Programming Language :: Python :: 3.12
Classifier: Programming Language :: Python :: 3.13
Classifier: Topic :: Scientific/Engineering :: Artificial Intelligence
Requires-Python: >=3.11
Requires-Dist: chex>=0.1.0
Requires-Dist: jax>=0.8.1
Requires-Dist: jaxlib>=0.8.1
Requires-Dist: treescope
Provides-Extra: dev
Requires-Dist: pyink; extra == 'dev'
Requires-Dist: pyrefly; extra == 'dev'
Requires-Dist: pytest; extra == 'dev'
Requires-Dist: pytest-cov; extra == 'dev'
Requires-Dist: ruff; extra == 'dev'
